AioSpider/__init__.py
AioSpider/__version__
AioSpider/aioSpider.py
AioSpider/browser.py
AioSpider/constants.py
AioSpider/requirements.txt
AioSpider/settings.py
AioSpider/setup.py
AioSpider/signals.py
AioSpider/cmd/__init__.py
AioSpider/cmd/args.py
AioSpider/cmd/cmd.py
AioSpider/cmd/crawl.py
AioSpider/cmd/create.py
AioSpider/cmd/make.py
AioSpider/cmd/options.py
AioSpider/cmd/server.py
AioSpider/cmd/test.py
AioSpider/core/__init__.py
AioSpider/core/concurrency_strategy.py
AioSpider/core/engine.py
AioSpider/core/event.py
AioSpider/core/patch.py
AioSpider/core/signals.py
AioSpider/core/task_queue.py
AioSpider/datamanager/__init__.py
AioSpider/datamanager/commit.py
AioSpider/datamanager/data_manager.py
AioSpider/datamanager/filter.py
AioSpider/datamanager/init.py
AioSpider/db/__init__.py
AioSpider/db/abc/__init__.py
AioSpider/db/abc/async_abc.py
AioSpider/db/abc/sync_abc.py
AioSpider/db/csv/__init__.py
AioSpider/db/csv/csv.py
AioSpider/db/mongo/__init__.py
AioSpider/db/mongo/async_mongo.py
AioSpider/db/mongo/sync_mongo.py
AioSpider/db/mysql/__init__.py
AioSpider/db/mysql/async_mysql.py
AioSpider/db/mysql/sync_mysql.py
AioSpider/db/redis/__init__.py
AioSpider/db/redis/async_lock.py
AioSpider/db/redis/async_redis.py
AioSpider/db/redis/sync_redis.py
AioSpider/db/sql/__init__.py
AioSpider/db/sql/base.py
AioSpider/db/sql/mysql/__init__.py
AioSpider/db/sql/mysql/sql.py
AioSpider/db/sql/sqlite/__init__.py
AioSpider/db/sql/sqlite/sql.py
AioSpider/db/sqlite/__init__.py
AioSpider/db/sqlite/async_sqlite.py
AioSpider/db/sqlite/sync_sqlite.py
AioSpider/downloader/__init__.py
AioSpider/downloader/abc.py
AioSpider/downloader/aiohttp_module.py
AioSpider/downloader/downloader.py
AioSpider/downloader/httpx_module.py
AioSpider/downloader/requests_module.py
AioSpider/exceptions/__init__.py
AioSpider/exceptions/error_codes.py
AioSpider/exceptions/exceptions.py
AioSpider/exceptions/orm_error.py
AioSpider/exceptions/schedule_error.py
AioSpider/field/__init__.py
AioSpider/field/datefield.py
aiospider_tarkin-1.9.15.dist-info/licenses/LICENSE
aiospider_tarkin-1.9.15.dist-info/METADATA
aiospider_tarkin-1.9.15.dist-info/WHEEL
aiospider_tarkin-1.9.15.dist-info/entry_points.txt
aiospider_tarkin-1.9.15.dist-info/top_level.txt
aiospider_tarkin-1.9.15.dist-info/RECORD
