Metadata-Version: 2.4
Name: AioSpider-tarkin
Version: 1.9.15
Summary: 基于 asyncio 的高性能异步爬虫框架，支持 MySQL/MongoDB/Redis 等多种数据存储
Home-page: https://github.com/yourusername/AioSpider-tarkin
Author: Tarkin
Author-email: 
License: MIT
Project-URL: Homepage, https://github.com/yourusername/AioSpider-tarkin
Project-URL: Documentation, https://github.com/yourusername/AioSpider-tarkin
Project-URL: Repository, https://github.com/yourusername/AioSpider-tarkin
Project-URL: Issues, https://github.com/yourusername/AioSpider-tarkin/issues
Keywords: spider,crawler,async,asyncio,aiohttp,mysql,mongodb,redis,web scraping,data collection
Classifier: Development Status :: 4 - Beta
Classifier: Intended Audience :: Developers
Classifier: License :: OSI Approved :: MIT License
Classifier: Programming Language :: Python :: 3
Classifier: Programming Language :: Python :: 3.8
Classifier: Programming Language :: Python :: 3.9
Classifier: Programming Language :: Python :: 3.10
Classifier: Programming Language :: Python :: 3.11
Classifier: Programming Language :: Python :: 3.12
Classifier: Topic :: Software Development :: Libraries :: Python Modules
Classifier: Topic :: Internet :: WWW/HTTP
Classifier: Topic :: Software Development :: Libraries :: Application Frameworks
Requires-Python: >=3.8
License-File: LICENSE
Requires-Dist: attrs>=24.2.0
Requires-Dist: idna>=3.6
Requires-Dist: six>=1.16.0
Requires-Dist: typing_extensions>=4.9.0
Requires-Dist: aiocsv>=1.2.4
Requires-Dist: aiofiles>=23.2.1
Requires-Dist: aiohttp>=3.9.1
Requires-Dist: aiomysql>=0.2.0
Requires-Dist: aioredis>=2.0.1
Requires-Dist: aiosqlite>=0.19.0
Requires-Dist: motor>=3.3.1
Requires-Dist: beautifulsoup4>=4.12.2
Requires-Dist: bitarray>=2.8.2
Requires-Dist: chardet>=5.2.0
Requires-Dist: loguru>=0.7.2
Requires-Dist: lxml<5.0.0,>=4.9.3
Requires-Dist: pydash>=7.0.6
Requires-Dist: PyExecJS>=1.5.1
Requires-Dist: pymongo>=4.5.0
Requires-Dist: pymysql>=1.1.0
Requires-Dist: redis>=5.0.1
Requires-Dist: requests>=2.32.0
Requires-Dist: retry>=0.9.2
Requires-Dist: rsa>=4.9
Requires-Dist: psutil>=6.0.0
Requires-Dist: httpx>=0.27.2
Requires-Dist: w3lib>=2.2.1
Requires-Dist: aiosmtplib>=3.0.2
Requires-Dist: pycryptodome>=3.19.0
Requires-Dist: pandas>=2.0.3
Requires-Dist: demjson3>=3.0.0
Requires-Dist: tqdm>=4.65.0
Requires-Dist: selenium>=4.14.0
Requires-Dist: playwright>=1.39.0
Provides-Extra: cchardet
Requires-Dist: cchardet>=2.1.7; extra == "cchardet"
Provides-Extra: mariadb
Requires-Dist: mariadb>=1.1.10; extra == "mariadb"
Provides-Extra: oracle
Requires-Dist: cx_Oracle>=8.3.0; extra == "oracle"
Provides-Extra: postgresql
Requires-Dist: psycopg2-binary>=2.9.10; extra == "postgresql"
Requires-Dist: asyncpg>=0.30.0; extra == "postgresql"
Provides-Extra: sqlserver
Requires-Dist: pyodbc>=5.2.0; extra == "sqlserver"
Requires-Dist: aioodbc>=0.5.0; extra == "sqlserver"
Provides-Extra: full
Requires-Dist: cchardet>=2.1.7; extra == "full"
Requires-Dist: mariadb>=1.1.10; extra == "full"
Requires-Dist: cx_Oracle>=8.3.0; extra == "full"
Requires-Dist: psycopg2-binary>=2.9.10; extra == "full"
Requires-Dist: asyncpg>=0.30.0; extra == "full"
Requires-Dist: pyodbc>=5.2.0; extra == "full"
Requires-Dist: aioodbc>=0.5.0; extra == "full"
Dynamic: home-page
Dynamic: license-file
Dynamic: requires-python
